collective.behavior.talcondition-1.1.0-py3.11-nspkg.pth
collective/behavior/talcondition/__init__.py
collective/behavior/talcondition/behavior.py
collective/behavior/talcondition/configure.zcml
collective/behavior/talcondition/extender.py
collective/behavior/talcondition/interfaces.py
collective/behavior/talcondition/setuphandlers.py
collective/behavior/talcondition/testing.py
collective/behavior/talcondition/testing.zcml
collective/behavior/talcondition/utils.py
collective/behavior/talcondition/locales/es/LC_MESSAGES/collective.behavior.talcondition.po
collective/behavior/talcondition/locales/fr/LC_MESSAGES/collective.behavior.talcondition.po
collective/behavior/talcondition/profiles/default/browserlayer.xml
collective/behavior/talcondition/profiles/default/collectivebehaviortalcondition_marker.txt
collective/behavior/talcondition/profiles/default/metadata.xml
collective/behavior/talcondition/profiles/testing/metadata.xml
collective/behavior/talcondition/profiles/testing/types.xml
collective/behavior/talcondition/profiles/testing/types/testtype.xml
collective/behavior/talcondition/profiles/uninstall/browserlayer.xml
collective/behavior/talcondition/tests/__init__.py
collective/behavior/talcondition/tests/test_behavior.py
collective/behavior/talcondition/tests/test_extender.py
collective/behavior/talcondition/tests/test_robot.py
collective/behavior/talcondition/tests/test_setup.py
collective/behavior/talcondition/tests/test_utils.py
collective/behavior/talcondition/tests/robot/.gitkeep
collective.behavior.talcondition-1.1.0.dist-info/METADATA
collective.behavior.talcondition-1.1.0.dist-info/WHEEL
collective.behavior.talcondition-1.1.0.dist-info/entry_points.txt
collective.behavior.talcondition-1.1.0.dist-info/namespace_packages.txt
collective.behavior.talcondition-1.1.0.dist-info/top_level.txt
collective.behavior.talcondition-1.1.0.dist-info/RECORD
